{
  "context": "Eudicots",
  "governing_code": "ICN",
  "includes_approximate_matches": true,
  "includes_deprecated_taxa": false,
  "includes_suppressed_names": false,
  "matched_names": [
    "cotinus coggygria",
    "mangifera indica",
    "pistacia vera",
    "schinus molle",
    "commiphora abyssinica",
    "khaya senegalensis",
    "citrus limon",
    "citrus microcarpa",
    "citrus reticulata",
    "citrus sinensis",
    "bergera koenigii",
    "ruta chalepensis",
    "ruta graveolens",
    "acer buergerianum",
    "acer campestre",
    "acer capillipes",
    "acer cappadocicum",
    "acer carpinifolium",
    "acer griseum",
    "acer hyrcanum",
    "acer japonicum",
    "acer pictum subsp. mono",
    "acer monspessulanum",
    "acer negundo",
    "acer opalus",
    "acer palmatum",
    "acer rufinerve",
    "acer saccharinum",
    "acer saccharum",
    "acer sempervirens",
    "quassia amara",
    "anacardium occidentale",
    "haemotostaphis barteri",
    "lannea barteri",
    "pseudospondias microcarpa",
    "sclerocarya birrea",
    "spondias dulcis",
    "aspilia africana"
  ],
  "results": [
    {
      "matches": [
        {
          "is_approximate_match": false,
          "is_synonym": false,
          "matched_name": "Cotinus coggygria",
          "nomenclature_code": "ICN",
          "score": 1.0,
          "search_string": "cotinus coggygria",
          "taxon": {
            "flags": [],
            "is_suppressed": false,
            "is_suppressed_from_synth": false,
            "name": "Cotinus coggygria",
            "ott_id": 876714,
            "rank": "species",
            "source": "ott3.3draft1",
            "synonyms": [
              "? pendulus",
              "Cotinus cinerea",
              "Cotinus coggygria glabra",
              "Cotinus coggygria velutina",
              "Cotinus coriaria",
              "Cotinus cotinus",
              "Cotinus velutina",
              "Rhus cotinus",
              "Rhus cotinus purpurea",
              "Rhus laevis",
              "Rhus obovatifolia",
              "Rhus simplicifolia",
              "Rhus velutina"
            ],
            "tax_sources": [
              "ncbi:269719",
              "gbif:3190522",
              "irmng:11441216"
            ],
            "unique_name": "Cotinus coggygria"
          }
        }
      ],
      "name": "cotinus coggygria"
    },
    {
      "matches": [
        {
          "is_approximate_match": false,
          "is_synonym": false,
          "matched_name": "Mangifera indica",
          "nomenclature_code": "ICN",
          "score": 1.0,
          "search_string": "mangifera indica",
          "taxon": {
            "flags": [],
            "is_suppressed": false,
            "is_suppressed_from_synth": false,
            "name": "Mangifera indica",
            "ott_id": 807634,
            "rank": "species",
            "source": "ott3.3draft1",
            "synonyms": [
              "Mangifera amba",
              "Mangifera anisodora",
              "Mangifera austro-yunnanensis",
              "Mangifera domestica",
              "Mangifera gladiata",
              "Mangifera integrifolia",
              "Mangifera kukula",
              "Mangifera linnaei",
              "Mangifera maritima",
              "Mangifera mekongensis",
              "Mangifera montana",
              "Mangifera racemosa",
              "Mangifera rostrata",
              "Mangifera rubra",
              "Mangifera sativa",
              "Mangifera siamensis",
              "Mangifera viridis"
            ],
            "tax_sources": [
              "ncbi:29780",
              "gbif:3190638",
              "irmng:10201022"
            ],
            "unique_name": "Mangifera indica"
          }
        },
        {
          "is_approximate_match": false,
          "is_synonym": true,
          "matched_name": "Mangifera indica",
          "nomenclature_code": "ICN",
          "score": 1.0,
          "search_string": "mangifera indica",
          "taxon": {
            "flags": [],
            "is_suppressed": false,
            "is_suppressed_from_synth": false,
            "name": "Mangifera foetida",
            "ott_id": 422407,
            "rank": "species",
            "source": "ott3.3draft1",
            "synonyms": [
              "Mangifera horsfieldii",
              "Mangifera indica",
              "Mangifera leschenaultii"
            ],
            "tax_sources": [
              "ncbi:171935",
              "gbif:3190640",
              "irmng:11427926"
            ],
            "unique_name": "Mangifera foetida"
          }
        },
        {
          "is_approximate_match": false,
          "is_synonym": true,
          "matched_name": "Mangifera indica",
          "nomenclature_code": "ICN",
          "score": 1.0,
          "search_string": "mangifera indica",
          "taxon": {
            "flags": [],
            "is_suppressed": false,
            "is_suppressed_from_synth": false,
            "name": "Mangifera sylvatica",
            "ott_id": 847341,
            "rank": "species",
            "source": "ott3.3draft1",
            "synonyms": [
              "Mangifera indica"
            ],
            "tax_sources": [
              "ncbi:171944",
              "gbif:3662046"
            ],
            "unique_name": "Mangifera sylvatica"
          }
        }
      ],
      "name": "mangifera indica"
    },
    {
      "matches": [
        {
          "is_approximate_match": false,
          "is_synonym": false,
          "matched_name": "Pistacia vera",
          "nomenclature_code": "ICN",
          "score": 1.0,
          "search_string": "pistacia vera",
          "taxon": {
            "flags": [],
            "is_suppressed": false,
            "is_suppressed_from_synth": false,
            "name": "Pistacia vera",
            "ott_id": 200787,
            "rank": "species",
            "source": "ott3.3draft1",
            "synonyms": [
              "Lentiscus vera",
              "Pistacia badghysi",
              "Pistacia macrophylla",
              "Pistacia narbonensis",
              "Pistacia nigricans",
              "Pistacia officinarum",
              "Pistacia reticulata",
              "Pistacia trifolia",
              "Pistacia variifolia"
            ],
            "tax_sources": [
              "ncbi:55513",
              "gbif:3190585",
              "irmng:10206336"
            ],
            "unique_name": "Pistacia vera"
          }
        }
      ],
      "name": "pistacia vera"
    },
    {
      "matches": [
        {
          "is_approximate_match": false,
          "is_synonym": false,
          "matched_name": "Schinus molle",
          "nomenclature_code": "ICN",
          "score": 1.0,
          "search_string": "schinus molle",
          "taxon": {
            "flags": [],
            "is_suppressed": false,
            "is_suppressed_from_synth": false,
            "name": "Schinus molle",
            "ott_id": 411495,
            "rank": "species",
            "source": "ott3.3draft1",
            "synonyms": [
              "Duvaua molle",
              "Duvaua velutina",
              "Lithraea molle",
              "Mauria schickendantzii",
              "Schinus bituminosus",
              "Schinus chilensis",
              "Schinus latifolius tomentosus",
              "Schinus sp. 'Savolainen 1997'",
              "Schinus velutinus"
            ],
            "tax_sources": [
              "ncbi:43851",
              "gbif:3190642",
              "irmng:11212753"
            ],
            "unique_name": "Schinus molle"
          }
        }
      ],
      "name": "schinus molle"
    },
    {
      "matches": [
        {
          "is_approximate_match": false,
          "is_synonym": false,
          "matched_name": "Commiphora abyssinica",
          "nomenclature_code": "ICN",
          "score": 1.0,
          "search_string": "commiphora abyssinica",
          "taxon": {
            "flags": [],
            "is_suppressed": false,
            "is_suppressed_from_synth": false,
            "name": "Commiphora abyssinica",
            "ott_id": 7641557,
            "rank": "species",
            "source": "ott3.3draft1",
            "synonyms": [],
            "tax_sources": [
              "gbif:8908080"
            ],
            "unique_name": "Commiphora abyssinica"
          }
        },
        {
          "is_approximate_match": false,
          "is_synonym": true,
          "matched_name": "Commiphora abyssinica",
          "nomenclature_code": "ICN",
          "score": 1.0,
          "search_string": "commiphora abyssinica",
          "taxon": {
            "flags": [],
            "is_suppressed": false,
            "is_suppressed_from_synth": false,
            "name": "Commiphora kua",
            "ott_id": 493265,
            "rank": "species",
            "source": "ott3.3draft1",
            "synonyms": [
              "Balsamea abyssinica",
              "Balsamodendron abyssinicum",
              "Balsamodendron kua",
              "Balsamodendrum habessinicum",
              "Balsamodendrum kafal",
              "Balsamus kafal",
              "Commiphora abyssinica",
              "Commiphora abyssinica crenulata",
              "Commiphora abyssinica simplicifolia",
              "Commiphora assaortensis",
              "Commiphora atramentaria",
              "Commiphora bruceae",
              "Commiphora candidula",
              "Commiphora crenulata",
              "Commiphora dancaliensis",
              "Commiphora ellenbeckii",
              "Commiphora flaviflora",
              "Commiphora gowlello",
              "Commiphora gracilispina",
              "Commiphora habessinica",
              "Commiphora habessinica crenulata",
              "Commiphora habessinica tanganyikensis",
              "Commiphora incisa",
              "Commiphora kua gowlello",
              "Commiphora lindensis",
              "Commiphora salubris",
              "Commiphora subsessilifolia"
            ],
            "tax_sources": [
              "ncbi:246356",
              "gbif:7286744"
            ],
            "unique_name": "Commiphora kua"
          }
        }
      ],
      "name": "commiphora abyssinica"
    },
    {
      "matches": [
        {
          "is_approximate_match": false,
          "is_synonym": false,
          "matched_name": "Khaya senegalensis",
          "nomenclature_code": "ICN",
          "score": 1.0,
          "search_string": "khaya senegalensis",
          "taxon": {
            "flags": [],
            "is_suppressed": false,
            "is_suppressed_from_synth": false,
            "name": "Khaya senegalensis",
            "ott_id": 923412,
            "rank": "species",
            "source": "ott3.3draft1",
            "synonyms": [
              "Swietenia senegalensis"
            ],
            "tax_sources": [
              "ncbi:587579",
              "gbif:3190508",
              "irmng:10857090"
            ],
            "unique_name": "Khaya senegalensis"
          }
        }
      ],
      "name": "khaya senegalensis"
    },
    {
      "matches": [
        {
          "is_approximate_match": false,
          "is_synonym": false,
          "matched_name": "Citrus limon",
          "nomenclature_code": "ICN",
          "score": 1.0,
          "search_string": "citrus limon",
          "taxon": {
            "flags": [
              "sibling_higher"
            ],
            "is_suppressed": false,
            "is_suppressed_from_synth": false,
            "name": "Citrus limon",
            "ott_id": 3942422,
            "rank": "species",
            "source": "ott3.3draft1",
            "synonyms": [
              "Citrus aurantium bergamia",
              "Citrus bergamia",
              "Citrus bergamota",
              "Citrus limodulcis",
              "Citrus limon pompia",
              "Citrus limonelloides",
              "Citrus limonia",
              "Citrus limonia otaitensis",
              "Citrus limonum",
              "Citrus medica limon",
              "Citrus medica limonum",
              "Citrus mellarosa",
              "Citrus meyeri",
              "Citrus volkameriana",
              "Citrus vulgaris",
              "Citrus x limon",
              "Limon vulgaris"
            ],
            "tax_sources": [
              "ncbi:2708",
              "gbif:3190171",
              "irmng:10200757"
            ],
            "unique_name": "Citrus limon"
          }
        }
      ],
      "name": "citrus limon"
    },
    {
      "matches": [
        {
          "is_approximate_match": false,
          "is_synonym": true,
          "matched_name": "Citrus microcarpa",
          "nomenclature_code": "ICN",
          "score": 1.0,
          "search_string": "citrus microcarpa",
          "taxon": {
            "flags": [
              "hybrid",
              "sibling_higher"
            ],
            "is_suppressed": false,
            "is_suppressed_from_synth": true,
            "name": "Citrus x microcarpa",
            "ott_id": 5146049,
            "rank": "species",
            "source": "ott3.3draft1",
            "synonyms": [
              "Citrofortunella microcarpa",
              "Citrofortunella mitis",
              "Citrus madurensis auct. non Lour., 1790",
              "Citrus microcarpa",
              "Citrus mitis",
              "Citrus reticulata x Fortunella japonica",
              "Citrus reticulata x Fortunella margarita",
              "x Citrofortunella microcarpa",
              "x Citrofortunella mitis",
              "\u00d7Citrofortunella mitis"
            ],
            "tax_sources": [
              "ncbi:164113",
              "gbif:3831218",
              "irmng:10941519"
            ],
            "unique_name": "Citrus x microcarpa"
          }
        }
      ],
      "name": "citrus microcarpa"
    },
    {
      "matches": [
        {
          "is_approximate_match": false,
          "is_synonym": false,
          "matched_name": "Citrus reticulata",
          "nomenclature_code": "ICN",
          "score": 1.0,
          "search_string": "citrus reticulata",
          "taxon": {
            "flags": [
              "sibling_higher"
            ],
            "is_suppressed": false,
            "is_suppressed_from_synth": false,
            "name": "Citrus reticulata",
            "ott_id": 37136,
            "rank": "species",
            "source": "ott3.3draft1",
            "synonyms": [
              "Citrus aurantium tachibana",
              "Citrus chachiensis",
              "Citrus chrysocarpa",
              "Citrus crenatifolia",
              "Citrus daoxianensis",
              "Citrus deliciosa",
              "Citrus depressa",
              "Citrus depressa vangasay",
              "Citrus erythrosa",
              "Citrus madurensis deliciosa",
              "Citrus madurensis vangasaye",
              "Citrus mangshanensis",
              "Citrus nippokoreana",
              "Citrus nobilis",
              "Citrus nobilis deliciosa",
              "Citrus nobilis koozi",
              "Citrus nobilis ponki",
              "Citrus nobilis sunki",
              "Citrus nobilis unshiu",
              "Citrus nobilis vangasaye",
              "Citrus ponki",
              "Citrus poonensis",
              "Citrus reticulata austera",
              "Citrus reticulata deliciosa",
              "Citrus reticulata tachibana",
              "Citrus reticulata unshiu",
              "Citrus succosa",
              "Citrus suhuiensis",
              "Citrus sunki",
              "Citrus tachibana",
              "Citrus tachibana depressa",
              "Citrus tachibana ponki",
              "Citrus tachibana suhuiensis",
              "Citrus tachibana sunki",
              "Citrus tangerina",
              "Citrus tankan",
              "Citrus unshiu",
              "Citrus vangasay",
              "Citrus vangasaye",
              "Citrus vangasy"
            ],
            "tax_sources": [
              "ncbi:85571",
              "gbif:3190172",
              "irmng:11303887"
            ],
            "unique_name": "Citrus reticulata"
          }
        }
      ],
      "name": "citrus reticulata"
    },
    {
      "matches": [
        {
          "is_approximate_match": false,
          "is_synonym": false,
          "matched_name": "Citrus sinensis",
          "nomenclature_code": "ICN",
          "score": 1.0,
          "search_string": "citrus sinensis",
          "taxon": {
            "flags": [
              "sibling_higher"
            ],
            "is_suppressed": false,
            "is_suppressed_from_synth": false,
            "name": "Citrus sinensis",
            "ott_id": 3942433,
            "rank": "species",
            "source": "ott3.3draft1",
            "synonyms": [
              "Citrus x sinensis"
            ],
            "tax_sources": [
              "ncbi:2711",
              "irmng:11193531"
            ],
            "unique_name": "Citrus sinensis"
          }
        },
        {
          "is_approximate_match": false,
          "is_synonym": true,
          "matched_name": "Citrus sinensis",
          "nomenclature_code": "ICN",
          "score": 1.0,
          "search_string": "citrus sinensis",
          "taxon": {
            "flags": [
              "sibling_higher"
            ],
            "is_suppressed": false,
            "is_suppressed_from_synth": false,
            "name": "Citrus aurantium",
            "ott_id": 3942423,
            "rank": "species",
            "source": "ott3.3draft1",
            "synonyms": [
              "Aurantium acre",
              "Aurantium corniculatum",
              "Aurantium distortum",
              "Aurantium humile",
              "Aurantium myrtifolium",
              "Aurantium sinense",
              "Aurantium vulgare",
              "Citrus amara",
              "Citrus aurantium aurantium",
              "Citrus aurantium bigaradia",
              "Citrus aurantium myrtifolia",
              "Citrus aurantium vulgaris",
              "Citrus aurata",
              "Citrus bergamia",
              "Citrus bigaradia",
              "Citrus changshan-huyou",
              "Citrus communis",
              "Citrus daidai",
              "Citrus decumana paradisi",
              "Citrus decumana pationiana",
              "Citrus decumana racemosa",
              "Citrus dulcis",
              "Citrus florida",
              "Citrus grandis racemosa",
              "Citrus humilis",
              "Citrus madraspatana",
              "Citrus maxima urocarpa",
              "Citrus maxima uvacarpa",
              "Citrus myrtifolia",
              "Citrus nobilis",
              "Citrus paradisi",
              "Citrus reticulata x Citrus maxima",
              "Citrus sinensis",
              "Citrus sinensis crassa",
              "Citrus sinensis fetifera",
              "Citrus sinensis lusitanica",
              "Citrus taiwanica",
              "Citrus tangelo",
              "Citrus vulgaris",
              "Citrus x aurantium",
              "Citrus xparadisi"
            ],
            "tax_sources": [
              "ncbi:43166",
              "gbif:8077391",
              "irmng:10206580",
              "irmng:11440111"
            ],
            "unique_name": "Citrus aurantium"
          }
        }
      ],
      "name": "citrus sinensis"
    },
    {
      "matches": [
        {
          "is_approximate_match": false,
          "is_synonym": false,
          "matched_name": "Bergera koenigii",
          "nomenclature_code": "ICN",
          "score": 1.0,
          "search_string": "bergera koenigii",
          "taxon": {
            "flags": [],
            "is_suppressed": false,
            "is_suppressed_from_synth": false,
            "name": "Bergera koenigii",
            "ott_id": 321836,
            "rank": "species",
            "source": "ott3.3draft1",
            "synonyms": [
              "Murraya koenigii"
            ],
            "tax_sources": [
              "ncbi:159030",
              "irmng:11305102"
            ],
            "unique_name": "Bergera koenigii"
          }
        }
      ],
      "name": "bergera koenigii"
    },
    {
      "matches": [
        {
          "is_approximate_match": false,
          "is_synonym": false,
          "matched_name": "Ruta chalepensis",
          "nomenclature_code": "ICN",
          "score": 1.0,
          "search_string": "ruta chalepensis",
          "taxon": {
            "flags": [],
            "is_suppressed": false,
            "is_suppressed_from_synth": false,
            "name": "Ruta chalepensis",
            "ott_id": 504804,
            "rank": "species",
            "source": "ott3.3draft1",
            "synonyms": [],
            "tax_sources": [
              "ncbi:452790",
              "gbif:3190381",
              "irmng:10201628"
            ],
            "unique_name": "Ruta chalepensis"
          }
        },
        {
          "is_approximate_match": false,
          "is_synonym": true,
          "matched_name": "Ruta chalepensis",
          "nomenclature_code": "ICN",
          "score": 1.0,
          "search_string": "ruta chalepensis",
          "taxon": {
            "flags": [],
            "is_suppressed": false,
            "is_suppressed_from_synth": false,
            "name": "Ruta graveolens",
            "ott_id": 596623,
            "rank": "species",
            "source": "ott3.3draft1",
            "synonyms": [
              "Ruta altera",
              "Ruta chalepensis",
              "Ruta ciliata",
              "Ruta crithmifolia",
              "Ruta divaricata",
              "Ruta graveolens angustifolia",
              "Ruta graveolens divaricata",
              "Ruta graveolens hortensis",
              "Ruta holopetala",
              "Ruta hortensis",
              "Ruta intermedia",
              "Ruta officinalis"
            ],
            "tax_sources": [
              "ncbi:37565",
              "gbif:3190382",
              "irmng:11130156"
            ],
            "unique_name": "Ruta graveolens"
          }
        }
      ],
      "name": "ruta chalepensis"
    },
    {
      "matches": [
        {
          "is_approximate_match": false,
          "is_synonym": false,
          "matched_name": "Ruta graveolens",
          "nomenclature_code": "ICN",
          "score": 1.0,
          "search_string": "ruta graveolens",
          "taxon": {
            "flags": [],
            "is_suppressed": false,
            "is_suppressed_from_synth": false,
            "name": "Ruta graveolens",
            "ott_id": 596623,
            "rank": "species",
            "source": "ott3.3draft1",
            "synonyms": [
              "Ruta altera",
              "Ruta chalepensis",
              "Ruta ciliata",
              "Ruta crithmifolia",
              "Ruta divaricata",
              "Ruta graveolens angustifolia",
              "Ruta graveolens divaricata",
              "Ruta graveolens hortensis",
              "Ruta holopetala",
              "Ruta hortensis",
              "Ruta intermedia",
              "Ruta officinalis"
            ],
            "tax_sources": [
              "ncbi:37565",
              "gbif:3190382",
              "irmng:11130156"
            ],
            "unique_name": "Ruta graveolens"
          }
        }
      ],
      "name": "ruta graveolens"
    },
    {
      "matches": [
        {
          "is_approximate_match": false,
          "is_synonym": false,
          "matched_name": "Acer buergerianum",
          "nomenclature_code": "ICN",
          "score": 1.0,
          "search_string": "acer buergerianum",
          "taxon": {
            "flags": [],
            "is_suppressed": false,
            "is_suppressed_from_synth": false,
            "name": "Acer buergerianum",
            "ott_id": 979924,
            "rank": "species",
            "source": "ott3.3draft1",
            "synonyms": [
              "Acer buergeranum",
              "Acer buergerianum jiujiangense",
              "Acer buergerianum trinerve",
              "Acer lingii",
              "Acer palmatum subtrilobum",
              "Acer subtrilobum",
              "Acer trifidum",
              "Acer trifidum buergerianum",
              "Acer trifidum elobatum",
              "Acer trinerve"
            ],
            "tax_sources": [
              "ncbi:57649",
              "gbif:7100404"
            ],
            "unique_name": "Acer buergerianum"
          }
        }
      ],
      "name": "acer buergerianum"
    },
    {
      "matches": [
        {
          "is_approximate_match": false,
          "is_synonym": false,
          "matched_name": "Acer campestre",
          "nomenclature_code": "ICN",
          "score": 1.0,
          "search_string": "acer campestre",
          "taxon": {
            "flags": [],
            "is_suppressed": false,
            "is_suppressed_from_synth": false,
            "name": "Acer campestre",
            "ott_id": 506137,
            "rank": "species",
            "source": "ott3.3draft1",
            "synonyms": [
              "Acer campestre pulverulentum",
              "Acer campestre suberosum",
              "Acer tomentosum",
              "Acer trattinickii",
              "Acer vulgare"
            ],
            "tax_sources": [
              "ncbi:66205",
              "gbif:3189863",
              "irmng:11307082"
            ],
            "unique_name": "Acer campestre"
          }
        }
      ],
      "name": "acer campestre"
    },
    {
      "matches": [
        {
          "is_approximate_match": false,
          "is_synonym": false,
          "matched_name": "Acer capillipes",
          "nomenclature_code": "ICN",
          "score": 1.0,
          "search_string": "acer capillipes",
          "taxon": {
            "flags": [],
            "is_suppressed": false,
            "is_suppressed_from_synth": false,
            "name": "Acer capillipes",
            "ott_id": 190369,
            "rank": "species",
            "source": "ott3.3draft1",
            "synonyms": [
              "Acer pensylvanicum capillipes"
            ],
            "tax_sources": [
              "ncbi:171205",
              "gbif:7495204"
            ],
            "unique_name": "Acer capillipes"
          }
        }
      ],
      "name": "acer capillipes"
    },
    {
      "matches": [
        {
          "is_approximate_match": false,
          "is_synonym": false,
          "matched_name": "Acer cappadocicum",
          "nomenclature_code": "ICN",
          "score": 1.0,
          "search_string": "acer cappadocicum",
          "taxon": {
            "flags": [],
            "is_suppressed": false,
            "is_suppressed_from_synth": false,
            "name": "Acer cappadocicum",
            "ott_id": 1055367,
            "rank": "species",
            "source": "ott3.3draft1",
            "synonyms": [
              "Acer cappadocicum rubrum"
            ],
            "tax_sources": [
              "ncbi:169053",
              "gbif:7262908"
            ],
            "unique_name": "Acer cappadocicum"
          }
        }
      ],
      "name": "acer cappadocicum"
    },
    {
      "matches": [
        {
          "is_approximate_match": false,
          "is_synonym": false,
          "matched_name": "Acer carpinifolium",
          "nomenclature_code": "ICN",
          "score": 1.0,
          "search_string": "acer carpinifolium",
          "taxon": {
            "flags": [],
            "is_suppressed": false,
            "is_suppressed_from_synth": false,
            "name": "Acer carpinifolium",
            "ott_id": 774549,
            "rank": "species",
            "source": "ott3.3draft1",
            "synonyms": [
              "Acer binatum",
              "Acer japonicum carpinifolium"
            ],
            "tax_sources": [
              "ncbi:66206",
              "gbif:3768602"
            ],
            "unique_name": "Acer carpinifolium"
          }
        }
      ],
      "name": "acer carpinifolium"
    },
    {
      "matches": [
        {
          "is_approximate_match": false,
          "is_synonym": false,
          "matched_name": "Acer griseum",
          "nomenclature_code": "ICN",
          "score": 1.0,
          "search_string": "acer griseum",
          "taxon": {
            "flags": [],
            "is_suppressed": false,
            "is_suppressed_from_synth": false,
            "name": "Acer griseum",
            "ott_id": 523216,
            "rank": "species",
            "source": "ott3.3draft1",
            "synonyms": [
              "Acer nikoense griseum",
              "Acer pedunculatum",
              "Crula grisea"
            ],
            "tax_sources": [
              "ncbi:168561",
              "gbif:3768452"
            ],
            "unique_name": "Acer griseum"
          }
        }
      ],
      "name": "acer griseum"
    },
    {
      "matches": [
        {
          "is_approximate_match": false,
          "is_synonym": false,
          "matched_name": "Acer hyrcanum",
          "nomenclature_code": "ICN",
          "score": 1.0,
          "search_string": "acer hyrcanum",
          "taxon": {
            "flags": [],
            "is_suppressed": false,
            "is_suppressed_from_synth": false,
            "name": "Acer hyrcanum",
            "ott_id": 830656,
            "rank": "species",
            "source": "ott3.3draft1",
            "synonyms": [],
            "tax_sources": [
              "ncbi:290838",
              "gbif:7262979"
            ],
            "unique_name": "Acer hyrcanum"
          }
        }
      ],
      "name": "acer hyrcanum"
    },
    {
      "matches": [
        {
          "is_approximate_match": false,
          "is_synonym": false,
          "matched_name": "Acer japonicum",
          "nomenclature_code": "ICN",
          "score": 1.0,
          "search_string": "acer japonicum",
          "taxon": {
            "flags": [],
            "is_suppressed": false,
            "is_suppressed_from_synth": false,
            "name": "Acer japonicum",
            "ott_id": 814702,
            "rank": "species",
            "source": "ott3.3draft1",
            "synonyms": [
              "Acer circumlobatum",
              "Acer circumlobatum insulare",
              "Acer heyhachii",
              "Acer insulare",
              "Acer japonicum insulare",
              "Acer japonicum kobakoense",
              "Acer kobakoense",
              "Acer monocarpon"
            ],
            "tax_sources": [
              "ncbi:47966",
              "gbif:8010851"
            ],
            "unique_name": "Acer japonicum"
          }
        }
      ],
      "name": "acer japonicum"
    },
    {
      "matches": [
        {
          "is_approximate_match": false,
          "is_synonym": false,
          "matched_name": "Acer pictum subsp. mono",
          "nomenclature_code": "ICN",
          "score": 1.0,
          "search_string": "acer pictum subsp. mono",
          "taxon": {
            "flags": [
              "infraspecific"
            ],
            "is_suppressed": false,
            "is_suppressed_from_synth": false,
            "name": "Acer pictum subsp. mono",
            "ott_id": 1050917,
            "rank": "subspecies",
            "source": "ott3.3draft1",
            "synonyms": [
              "Acer mono",
              "Acer mono subsp. mono"
            ],
            "tax_sources": [
              "ncbi:47963"
            ],
            "unique_name": "Acer pictum subsp. mono"
          }
        }
      ],
      "name": "acer pictum subsp. mono"
    },
    {
      "matches": [
        {
          "is_approximate_match": false,
          "is_synonym": false,
          "matched_name": "Acer monspessulanum",
          "nomenclature_code": "ICN",
          "score": 1.0,
          "search_string": "acer monspessulanum",
          "taxon": {
            "flags": [],
            "is_suppressed": false,
            "is_suppressed_from_synth": false,
            "name": "Acer monspessulanum",
            "ott_id": 636269,
            "rank": "species",
            "source": "ott3.3draft1",
            "synonyms": [
              "Acer monspessulanum cassinense"
            ],
            "tax_sources": [
              "ncbi:168566",
              "gbif:7262958"
            ],
            "unique_name": "Acer monspessulanum"
          }
        }
      ],
      "name": "acer monspessulanum"
    },
    {
      "matches": [
        {
          "is_approximate_match": false,
          "is_synonym": false,
          "matched_name": "Acer negundo",
          "nomenclature_code": "ICN",
          "score": 1.0,
          "search_string": "acer negundo",
          "taxon": {
            "flags": [],
            "is_suppressed": false,
            "is_suppressed_from_synth": false,
            "name": "Acer negundo",
            "ott_id": 948925,
            "rank": "species",
            "source": "ott3.3draft1",
            "synonyms": [
              "Acer californica",
              "Acer interius",
              "Acer negundo auratum",
              "Acer negundo aureovariegatum",
              "Acer negundo negundo",
              "Negundo aceroides",
              "Negundo californica",
              "Negundo californicum",
              "Negundo fraxinifolium violaceum",
              "Negundo interius",
              "Negundo mexicanum",
              "Negundo negundo",
              "Negundo trifoliatum",
              "Rulac negundo",
              "Rulac texana"
            ],
            "tax_sources": [
              "ncbi:4023",
              "gbif:3189866",
              "irmng:11362328"
            ],
            "unique_name": "Acer negundo"
          }
        }
      ],
      "name": "acer negundo"
    },
    {
      "matches": [
        {
          "is_approximate_match": false,
          "is_synonym": false,
          "matched_name": "Acer opalus",
          "nomenclature_code": "ICN",
          "score": 1.0,
          "search_string": "acer opalus",
          "taxon": {
            "flags": [],
            "is_suppressed": false,
            "is_suppressed_from_synth": false,
            "name": "Acer opalus",
            "ott_id": 636271,
            "rank": "species",
            "source": "ott3.3draft1",
            "synonyms": [
              "Acer hispanicum",
              "Acer hispanicum montsiccianum",
              "Acer italum",
              "Acer leptopterum",
              "Acer microphyllum",
              "Acer montanum",
              "Acer opalus glabrescens",
              "Acer opalus glaucum",
              "Acer opalus hispanicum",
              "Acer opalus italum",
              "Acer opalus montsiccianum",
              "Acer opalus pubescens",
              "Acer opalus variabile",
              "Acer opulifolium",
              "Acer rotundifolium",
              "Acer tomentosum"
            ],
            "tax_sources": [
              "ncbi:168567",
              "gbif:7100278"
            ],
            "unique_name": "Acer opalus"
          }
        }
      ],
      "name": "acer opalus"
    },
    {
      "matches": [
        {
          "is_approximate_match": false,
          "is_synonym": false,
          "matched_name": "Acer palmatum",
          "nomenclature_code": "ICN",
          "score": 1.0,
          "search_string": "acer palmatum",
          "taxon": {
            "flags": [],
            "is_suppressed": false,
            "is_suppressed_from_synth": false,
            "name": "Acer palmatum",
            "ott_id": 506130,
            "rank": "species",
            "source": "ott3.3draft1",
            "synonyms": [
              "? eupalmatum",
              "Acer dissectum",
              "Acer eupalmatum",
              "Acer formosum",
              "Acer japonicum polymorphum",
              "Acer jucundum",
              "Acer palmatum amabile",
              "Acer palmatum atropurpureum",
              "Acer palmatum dissectum",
              "Acer palmatum hakonense",
              "Acer palmatum pilosum",
              "Acer palmatum plicatum",
              "Acer palmatum pubescens",
              "Acer palmatum quinquelobum",
              "Acer palmatum sanguineum",
              "Acer palmatum spectabile",
              "Acer palmatum thunbergii",
              "Acer polymorphum",
              "Acer polymorphum palmatum",
              "Acer polymorphum thunbergii",
              "Acer roseomarginatum eupalmatum",
              "Acer sanguineum",
              "Acer sessilifolium",
              "Negundo sessilifolium"
            ],
            "tax_sources": [
              "ncbi:66201",
              "gbif:7912328",
              "irmng:11004165"
            ],
            "unique_name": "Acer palmatum"
          }
        },
        {
          "is_approximate_match": false,
          "is_synonym": true,
          "matched_name": "Acer palmatum",
          "nomenclature_code": "ICN",
          "score": 1.0,
          "search_string": "acer palmatum",
          "taxon": {
            "flags": [],
            "is_suppressed": false,
            "is_suppressed_from_synth": false,
            "name": "Acer macrophyllum",
            "ott_id": 538695,
            "rank": "species",
            "source": "ott3.3draft1",
            "synonyms": [
              "Acer auritum",
              "Acer coptophyllum",
              "Acer dactylophyllum",
              "Acer hemionitis",
              "Acer leptodactylon",
              "Acer macrophyllum kimballiae",
              "Acer macrophyllum kimballii",
              "Acer macrophyllum rubrifolium",
              "Acer murrayanum",
              "Acer palmatum",
              "Acer platypterum",
              "Acer politum",
              "Acer speciosum",
              "Acer stellatum"
            ],
            "tax_sources": [
              "ncbi:66211",
              "gbif:3189835",
              "irmng:10764527"
            ],
            "unique_name": "Acer macrophyllum"
          }
        }
      ],
      "name": "acer palmatum"
    },
    {
      "matches": [
        {
          "is_approximate_match": false,
          "is_synonym": false,
          "matched_name": "Acer rufinerve",
          "nomenclature_code": "ICN",
          "score": 1.0,
          "search_string": "acer rufinerve",
          "taxon": {
            "flags": [],
            "is_suppressed": false,
            "is_suppressed_from_synth": false,
            "name": "Acer rufinerve",
            "ott_id": 700437,
            "rank": "species",
            "source": "ott3.3draft1",
            "synonyms": [
              "Acer cucullobracteatum",
              "Acer rufinerve albolimbatum",
              "Acer rufinerve angustifolium",
              "Acer rufinerve marmoratum"
            ],
            "tax_sources": [
              "ncbi:66215",
              "gbif:7263145"
            ],
            "unique_name": "Acer rufinerve"
          }
        }
      ],
      "name": "acer rufinerve"
    },
    {
      "matches": [
        {
          "is_approximate_match": false,
          "is_synonym": false,
          "matched_name": "Acer saccharinum",
          "nomenclature_code": "ICN",
          "score": 1.0,
          "search_string": "acer saccharinum",
          "taxon": {
            "flags": [],
            "is_suppressed": false,
            "is_suppressed_from_synth": false,
            "name": "Acer saccharinum",
            "ott_id": 266103,
            "rank": "species",
            "source": "ott3.3draft1",
            "synonyms": [
              "Acer album",
              "Acer collinsonia",
              "Acer dasycarpum",
              "Acer eriocarpum",
              "Acer palliderubrum",
              "Acer pallidum",
              "Acer palmifolium",
              "Acer pavia",
              "Acer pulchrum",
              "Acer rubrum",
              "Acer saccharinum ahlesii",
              "Acer saccharinum laciniatum",
              "Acer saccharinum purpureocarpum",
              "Acer saccharinum variifolium",
              "Acer saccharinum wieri",
              "Acer saira",
              "Acer tomentosum",
              "Acer virginianum",
              "Acer wieri",
              "Argentacer saccharinum",
              "Saccharodendron saccharinum",
              "Saccharosphendamnus saccharinus"
            ],
            "tax_sources": [
              "ncbi:75745",
              "gbif:3189837",
              "irmng:10854932"
            ],
            "unique_name": "Acer saccharinum"
          }
        },
        {
          "is_approximate_match": false,
          "is_synonym": true,
          "matched_name": "Acer saccharinum",
          "nomenclature_code": "ICN",
          "score": 1.0,
          "search_string": "acer saccharinum",
          "taxon": {
            "flags": [],
            "is_suppressed": false,
            "is_suppressed_from_synth": false,
            "name": "Acer saccharum",
            "ott_id": 948916,
            "rank": "species",
            "source": "ott3.3draft1",
            "synonyms": [
              "Acer rugelii",
              "Acer saccharinum",
              "Acer saccharophorum",
              "Acer saccharophorum subvestitum",
              "Acer saccharum saccharum",
              "Saccharodendron saccharum"
            ],
            "tax_sources": [
              "ncbi:4024",
              "gbif:3189859",
              "irmng:10662376"
            ],
            "unique_name": "Acer saccharum"
          }
        }
      ],
      "name": "acer saccharinum"
    },
    {
      "matches": [
        {
          "is_approximate_match": false,
          "is_synonym": false,
          "matched_name": "Acer saccharum",
          "nomenclature_code": "ICN",
          "score": 1.0,
          "search_string": "acer saccharum",
          "taxon": {
            "flags": [],
            "is_suppressed": false,
            "is_suppressed_from_synth": false,
            "name": "Acer saccharum",
            "ott_id": 948916,
            "rank": "species",
            "source": "ott3.3draft1",
            "synonyms": [
              "Acer rugelii",
              "Acer saccharinum",
              "Acer saccharophorum",
              "Acer saccharophorum subvestitum",
              "Acer saccharum saccharum",
              "Saccharodendron saccharum"
            ],
            "tax_sources": [
              "ncbi:4024",
              "gbif:3189859",
              "irmng:10662376"
            ],
            "unique_name": "Acer saccharum"
          }
        }
      ],
      "name": "acer saccharum"
    },
    {
      "matches": [
        {
          "is_approximate_match": false,
          "is_synonym": false,
          "matched_name": "Acer sempervirens",
          "nomenclature_code": "ICN",
          "score": 1.0,
          "search_string": "acer sempervirens",
          "taxon": {
            "flags": [],
            "is_suppressed": false,
            "is_suppressed_from_synth": false,
            "name": "Acer sempervirens",
            "ott_id": 830658,
            "rank": "species",
            "source": "ott3.3draft1",
            "synonyms": [
              "Acer heterophyllum",
              "Acer humile",
              "Acer willkommii"
            ],
            "tax_sources": [
              "ncbi:290839",
              "gbif:3768609"
            ],
            "unique_name": "Acer sempervirens"
          }
        }
      ],
      "name": "acer sempervirens"
    },
    {
      "matches": [
        {
          "is_approximate_match": false,
          "is_synonym": false,
          "matched_name": "Quassia amara",
          "nomenclature_code": "ICN",
          "score": 1.0,
          "search_string": "quassia amara",
          "taxon": {
            "flags": [],
            "is_suppressed": false,
            "is_suppressed_from_synth": false,
            "name": "Quassia amara",
            "ott_id": 708243,
            "rank": "species",
            "source": "ott3.3draft1",
            "synonyms": [
              "Quassia alatifolia",
              "Quassia amara amara",
              "Quassia amara grandiflora",
              "Quassia amara paniculata",
              "Quassia crocea",
              "Quassia officinalis"
            ],
            "tax_sources": [
              "ncbi:43725",
              "gbif:3190647",
              "irmng:11122393"
            ],
            "unique_name": "Quassia amara"
          }
        }
      ],
      "name": "quassia amara"
    },
    {
      "matches": [
        {
          "is_approximate_match": false,
          "is_synonym": false,
          "matched_name": "Anacardium occidentale",
          "nomenclature_code": "ICN",
          "score": 1.0,
          "search_string": "anacardium occidentale",
          "taxon": {
            "flags": [],
            "is_suppressed": false,
            "is_suppressed_from_synth": false,
            "name": "Anacardium occidentale",
            "ott_id": 999426,
            "rank": "species",
            "source": "ott3.3draft1",
            "synonyms": [
              "Acajuba occidentalis",
              "Anacardium amilcarianum",
              "Anacardium curatellaefolium",
              "Anacardium kuhlmannianum",
              "Anacardium microcarpum",
              "Anacardium occidentale americanum",
              "Anacardium othonianum",
              "Anacardium rondonianum",
              "Cassuvium pomiferum",
              "Cassuvium reniforme",
              "Cassuvium solitarium"
            ],
            "tax_sources": [
              "ncbi:171929",
              "gbif:5421368",
              "irmng:11022124"
            ],
            "unique_name": "Anacardium occidentale"
          }
        }
      ],
      "name": "anacardium occidentale"
    },
    {
      "matches": [
        {
          "is_approximate_match": true,
          "is_synonym": false,
          "matched_name": "Haematostaphis barteri",
          "nomenclature_code": "ICN",
          "score": 0.9545454382896423,
          "search_string": "haemotostaphis barteri",
          "taxon": {
            "flags": [],
            "is_suppressed": false,
            "is_suppressed_from_synth": false,
            "name": "Haematostaphis barteri",
            "ott_id": 6123907,
            "rank": "species",
            "source": "ott3.3draft1",
            "synonyms": [
              "Haematostaphis pierreana",
              "Haematostaphis purpurascens"
            ],
            "tax_sources": [
              "gbif:3662214"
            ],
            "unique_name": "Haematostaphis barteri"
          }
        }
      ],
      "name": "haemotostaphis barteri"
    },
    {
      "matches": [
        {
          "is_approximate_match": false,
          "is_synonym": false,
          "matched_name": "Lannea barteri",
          "nomenclature_code": "ICN",
          "score": 1.0,
          "search_string": "lannea barteri",
          "taxon": {
            "flags": [],
            "is_suppressed": false,
            "is_suppressed_from_synth": false,
            "name": "Lannea barteri",
            "ott_id": 6123927,
            "rank": "species",
            "source": "ott3.3draft1",
            "synonyms": [
              "Calesiam barteri",
              "Lannea egregia",
              "Lannea kerstingii",
              "Odina barteri"
            ],
            "tax_sources": [
              "gbif:3661192"
            ],
            "unique_name": "Lannea barteri"
          }
        }
      ],
      "name": "lannea barteri"
    },
    {
      "matches": [
        {
          "is_approximate_match": false,
          "is_synonym": false,
          "matched_name": "Pseudospondias microcarpa",
          "nomenclature_code": "ICN",
          "score": 1.0,
          "search_string": "pseudospondias microcarpa",
          "taxon": {
            "flags": [],
            "is_suppressed": false,
            "is_suppressed_from_synth": false,
            "name": "Pseudospondias microcarpa",
            "ott_id": 4728705,
            "rank": "species",
            "source": "ott3.3draft1",
            "synonyms": [
              "Sorindeia obliquifoliolata",
              "Spondias angolensis",
              "Spondias microcarpa",
              "Spondias zanzee"
            ],
            "tax_sources": [
              "ncbi:1321805",
              "gbif:3660956"
            ],
            "unique_name": "Pseudospondias microcarpa"
          }
        }
      ],
      "name": "pseudospondias microcarpa"
    },
    {
      "matches": [
        {
          "is_approximate_match": false,
          "is_synonym": false,
          "matched_name": "Sclerocarya birrea",
          "nomenclature_code": "ICN",
          "score": 1.0,
          "search_string": "sclerocarya birrea",
          "taxon": {
            "flags": [],
            "is_suppressed": false,
            "is_suppressed_from_synth": false,
            "name": "Sclerocarya birrea",
            "ott_id": 456294,
            "rank": "species",
            "source": "ott3.3draft1",
            "synonyms": [],
            "tax_sources": [
              "ncbi:289766",
              "gbif:7160810"
            ],
            "unique_name": "Sclerocarya birrea"
          }
        }
      ],
      "name": "sclerocarya birrea"
    },
    {
      "matches": [
        {
          "is_approximate_match": false,
          "is_synonym": false,
          "matched_name": "Spondias dulcis",
          "nomenclature_code": "ICN",
          "score": 1.0,
          "search_string": "spondias dulcis",
          "taxon": {
            "flags": [],
            "is_suppressed": false,
            "is_suppressed_from_synth": false,
            "name": "Spondias dulcis",
            "ott_id": 988308,
            "rank": "species",
            "source": "ott3.3draft1",
            "synonyms": [
              "Chrysomelon pomiferum",
              "Cytheraea dulcis",
              "Evia acida",
              "Evia dulcis",
              "Poupartia dulcis",
              "Spondias acida",
              "Spondias cythera",
              "Spondias cytherea",
              "Spondias fragrans",
              "Spondias lutea",
              "Spondias therebintoides"
            ],
            "tax_sources": [
              "ncbi:43861",
              "gbif:7554845",
              "irmng:10195276"
            ],
            "unique_name": "Spondias dulcis"
          }
        }
      ],
      "name": "spondias dulcis"
    },
    {
      "matches": [
        {
          "is_approximate_match": false,
          "is_synonym": false,
          "matched_name": "Aspilia africana",
          "nomenclature_code": "ICN",
          "score": 1.0,
          "search_string": "aspilia africana",
          "taxon": {
            "flags": [],
            "is_suppressed": false,
            "is_suppressed_from_synth": false,
            "name": "Aspilia africana",
            "ott_id": 5794461,
            "rank": "species",
            "source": "ott3.3draft1",
            "synonyms": [
              "Aspilia africana africana"
            ],
            "tax_sources": [
              "gbif:5396273"
            ],
            "unique_name": "Aspilia africana"
          }
        }
      ],
      "name": "aspilia africana"
    },
    {
      "matches": [],
      "name": "na"
    }
  ],
  "taxonomy": {
    "author": "open tree of life project",
    "name": "ott",
    "source": "ott3.3draft1",
    "version": "3.3",
    "weburl": "https://tree.opentreeoflife.org/about/taxonomy-version/ott3.3"
  },
  "unambiguous_names": [
    "cotinus coggygria",
    "mangifera indica",
    "pistacia vera",
    "schinus molle",
    "commiphora abyssinica",
    "khaya senegalensis",
    "citrus limon",
    "citrus reticulata",
    "citrus sinensis",
    "bergera koenigii",
    "ruta chalepensis",
    "ruta graveolens",
    "acer buergerianum",
    "acer campestre",
    "acer capillipes",
    "acer cappadocicum",
    "acer carpinifolium",
    "acer griseum",
    "acer hyrcanum",
    "acer japonicum",
    "acer pictum subsp. mono",
    "acer monspessulanum",
    "acer negundo",
    "acer opalus",
    "acer palmatum",
    "acer rufinerve",
    "acer saccharinum",
    "acer saccharum",
    "acer sempervirens",
    "quassia amara",
    "anacardium occidentale",
    "haemotostaphis barteri",
    "lannea barteri",
    "pseudospondias microcarpa",
    "sclerocarya birrea",
    "spondias dulcis",
    "aspilia africana"
  ],
  "unmatched_names": [
    "na"
  ]
}
